imagen_pytorch/__init__.py
imagen_pytorch/cli.py
imagen_pytorch/configs.py
imagen_pytorch/data.py
imagen_pytorch/default_config.json
imagen_pytorch/elucidated_imagen.py
imagen_pytorch/imagen_pytorch.py
imagen_pytorch/imagen_video.py
imagen_pytorch/t5.py
imagen_pytorch/trainer.py
imagen_pytorch/utils.py
imagen_pytorch/version.py
imagen_pytorch/test/__init__.py
imagen_pytorch/test/test_trainer.py
imagen_pytorch-2.1.0.dist-info/LICENSE
imagen_pytorch-2.1.0.dist-info/METADATA
imagen_pytorch-2.1.0.dist-info/WHEEL
imagen_pytorch-2.1.0.dist-info/entry_points.txt
imagen_pytorch-2.1.0.dist-info/top_level.txt
imagen_pytorch-2.1.0.dist-info/RECORD
