Metadata-Version: 2.1
Name: imagen-pytorch
Version: 2.1.0
Summary: Imagen - unprecedented photorealism × deep level of language understanding
Home-page: https://github.com/lucidrains/imagen-pytorch
Author: Phil Wang
Author-email: lucidrains@gmail.com
License: MIT
Keywords: artificial intelligence,deep learning,transformers,text-to-image,denoising-diffusion
Classifier: Development Status :: 4 - Beta
Classifier: Intended Audience :: Developers
Classifier: Topic :: Scientific/Engineering :: Artificial Intelligence
Classifier: License :: OSI Approved :: MIT License
Classifier: Programming Language :: Python :: 3.6
License-File: LICENSE
Requires-Dist: accelerate >=0.23.0
Requires-Dist: beartype
Requires-Dist: click
Requires-Dist: datasets
Requires-Dist: einops >=0.7.0
Requires-Dist: ema-pytorch >=0.0.3
Requires-Dist: fsspec
Requires-Dist: kornia
Requires-Dist: numpy
Requires-Dist: packaging
Requires-Dist: pillow
Requires-Dist: pydantic >=2
Requires-Dist: pytorch-warmup
Requires-Dist: sentencepiece
Requires-Dist: torch >=1.6
Requires-Dist: torchvision
Requires-Dist: transformers
Requires-Dist: tqdm
